{
  "notreepunching:clay_tool": {
    "criteria": {
      "has_the_recipe": "2026-05-06 14:14:30 +1000"
    },
    "done": true
  },
  "notreepunching:diorite_cobblestone_wall": {
    "criteria": {
      "has_the_recipe": "2026-05-06 14:14:30 +1000"
    },
    "done": true
  },
  "iceandfire:iceandfire/root": {
    "criteria": {
      "tick": "2026-05-06 14:14:30 +1000"
    },
    "done": true
  },
  "notreepunching:stonecutting/granite_cobblestone_stairs": {
    "criteria": {
      "has_the_recipe": "2026-05-06 14:14:30 +1000"
    },
    "done": true
  },
  "notreepunching:sticks_from_logs_with_saw": {
    "criteria": {
      "has_the_recipe": "2026-05-06 14:14:30 +1000"
    },
    "done": true
  },
  "notreepunching:granite_cobblestone_stairs": {
    "criteria": {
      "has_the_recipe": "2026-05-06 14:14:30 +1000"
    },
    "done": true
  },
  "cold_sweat:recipes/goat_armor": {
    "criteria": {
      "has_boots_recipe": "2026-05-06 14:14:30 +1000"
    },
    "done": true
  },
  "takesapillage:root": {
    "criteria": {
      "always": "2026-05-06 14:14:30 +1000"
    },
    "done": true
  },
  "notreepunching:stonecutting/diorite_cobblestone_stairs": {
    "criteria": {
      "has_the_recipe": "2026-05-06 14:14:30 +1000"
    },
    "done": true
  },
  "notreepunching:diamond_saw": {
    "criteria": {
      "has_the_recipe": "2026-05-06 14:14:30 +1000"
    },
    "done": true
  },
  "notreepunching:flint_pickaxe": {
    "criteria": {
      "has_the_recipe": "2026-05-06 14:14:30 +1000"
    },
    "done": true
  },
  "notreepunching:sandstone_from_rocks": {
    "criteria": {
      "has_the_recipe": "2026-05-06 14:14:30 +1000"
    },
    "done": true
  },
  "notreepunching:netherite_mattock": {
    "criteria": {
      "has_the_recipe": "2026-05-06 14:14:30 +1000"
    },
    "done": true
  },
  "notreepunching:granite_cobblestone_slab": {
    "criteria": {
      "has_the_recipe": "2026-05-06 14:14:30 +1000"
    },
    "done": true
  },
  "notreepunching:plant_fiber_from_small_flowers_with_knife": {
    "criteria": {
      "has_the_recipe": "2026-05-06 14:14:30 +1000"
    },
    "done": true
  },
  "notreepunching:andesite_cobblestone_wall": {
    "criteria": {
      "has_the_recipe": "2026-05-06 14:14:30 +1000"
    },
    "done": true
  },
  "notreepunching:diorite_cobblestone_stairs": {
    "criteria": {
      "has_the_recipe": "2026-05-06 14:14:30 +1000"
    },
    "done": true
  },
  "notreepunching:gold_mattock": {
    "criteria": {
      "has_the_recipe": "2026-05-06 14:14:30 +1000"
    },
    "done": true
  },
  "notreepunching:diorite_cobblestone_from_rocks": {
    "criteria": {
      "has_the_recipe": "2026-05-06 14:14:30 +1000"
    },
    "done": true
  },
  "notreepunching:leather_from_chestplate_with_knife": {
    "criteria": {
      "has_the_recipe": "2026-05-06 14:14:30 +1000"
    },
    "done": true
  },
  "notreepunching:andesite_cobblestone_from_rocks": {
    "criteria": {
      "has_the_recipe": "2026-05-06 14:14:30 +1000"
    },
    "done": true
  },
  "cold_sweat:recipes/soulspring_lamp": {
    "criteria": {
      "has_recipe": "2026-05-06 14:14:30 +1000"
    },
    "done": true
  },
  "notreepunching:gold_saw": {
    "criteria": {
      "has_the_recipe": "2026-05-06 14:14:30 +1000"
    },
    "done": true
  },
  "the_finley_dimension_remastered:download_the_finley_dimension": {
    "criteria": {
      "download_the_finley_dimension_0": "2026-05-06 14:14:30 +1000"
    },
    "done": true
  },
  "notreepunching:leather_from_helmet_with_knife": {
    "criteria": {
      "has_the_recipe": "2026-05-06 14:14:30 +1000"
    },
    "done": true
  },
  "notreepunching:red_sandstone_from_rocks": {
    "criteria": {
      "has_the_recipe": "2026-05-06 14:14:30 +1000"
    },
    "done": true
  },
  "notreepunching:diorite_cobblestone_slab": {
    "criteria": {
      "has_the_recipe": "2026-05-06 14:14:30 +1000"
    },
    "done": true
  },
  "notreepunching:plant_string": {
    "criteria": {
      "has_the_recipe": "2026-05-06 14:14:30 +1000"
    },
    "done": true
  },
  "notreepunching:plant_fiber_from_tall_flowers_with_knife": {
    "criteria": {
      "has_the_recipe": "2026-05-06 14:14:30 +1000"
    },
    "done": true
  },
  "notreepunching:fire_starter": {
    "criteria": {
      "has_the_recipe": "2026-05-06 14:14:30 +1000"
    },
    "done": true
  },
  "ars_nouveau:root": {
    "criteria": {
      "ars_nouveau:worn_notebook": "2026-05-06 14:14:30 +1000"
    },
    "done": true
  },
  "notreepunching:plant_fiber_from_wheat_with_knife": {
    "criteria": {
      "has_the_recipe": "2026-05-06 14:14:30 +1000"
    },
    "done": true
  },
  "farmersdelight:main/root": {
    "criteria": {
      "seeds": "2026-05-06 14:14:30 +1000"
    },
    "done": true
  },
  "notreepunching:diamond_mattock": {
    "criteria": {
      "has_the_recipe": "2026-05-06 14:14:30 +1000"
    },
    "done": true
  },
  "notreepunching:sticks_from_planks_with_saw": {
    "criteria": {
      "has_the_recipe": "2026-05-06 14:14:30 +1000"
    },
    "done": true
  },
  "create:root": {
    "criteria": {
      "0": "2026-05-06 14:14:30 +1000"
    },
    "done": true
  },
  "naturescompass:natures_compass_log": {
    "criteria": {
      "has_recipe": "2026-05-06 14:14:30 +1000"
    },
    "done": true
  },
  "notreepunching:flint_knife": {
    "criteria": {
      "has_the_recipe": "2026-05-06 14:14:30 +1000"
    },
    "done": true
  },
  "notreepunching:clay_brick_from_balls": {
    "criteria": {
      "has_the_recipe": "2026-05-06 14:14:30 +1000"
    },
    "done": true
  },
  "cold_sweat:root": {
    "criteria": {
      "requirement": "2026-05-06 14:14:30 +1000"
    },
    "done": true
  },
  "notreepunching:granite_cobblestone_wall": {
    "criteria": {
      "has_the_recipe": "2026-05-06 14:14:30 +1000"
    },
    "done": true
  },
  "undergarden:undergarden/root": {
    "criteria": {
      "tick": "2026-05-06 14:14:30 +1000"
    },
    "done": true
  },
  "notreepunching:string_from_web_with_knife": {
    "criteria": {
      "has_the_recipe": "2026-05-06 14:14:30 +1000"
    },
    "done": true
  },
  "notreepunching:flint_hoe": {
    "criteria": {
      "has_the_recipe": "2026-05-06 14:14:30 +1000"
    },
    "done": true
  },
  "notreepunching:melon_slices_with_knife": {
    "criteria": {
      "has_the_recipe": "2026-05-06 14:14:30 +1000"
    },
    "done": true
  },
  "notreepunching:clay_brick_from_blocks": {
    "criteria": {
      "has_the_recipe": "2026-05-06 14:14:30 +1000"
    },
    "done": true
  },
  "notreepunching:macuahuitl": {
    "criteria": {
      "has_the_recipe": "2026-05-06 14:14:30 +1000"
    },
    "done": true
  },
  "notreepunching:gold_knife": {
    "criteria": {
      "has_the_recipe": "2026-05-06 14:14:30 +1000"
    },
    "done": true
  },
  "notreepunching:iron_mattock": {
    "criteria": {
      "has_the_recipe": "2026-05-06 14:14:30 +1000"
    },
    "done": true
  },
  "notreepunching:flint_shovel": {
    "criteria": {
      "has_the_recipe": "2026-05-06 14:14:30 +1000"
    },
    "done": true
  },
  "notreepunching:plant_fiber_from_sugarcane_with_knife": {
    "criteria": {
      "has_the_recipe": "2026-05-06 14:14:30 +1000"
    },
    "done": true
  },
  "naturescompass:natures_compass": {
    "criteria": {
      "has_recipe": "2026-05-06 14:14:30 +1000"
    },
    "done": true
  },
  "brewinandchewin:main/root": {
    "criteria": {
      "beer": "2026-05-06 14:14:30 +1000"
    },
    "done": true
  },
  "naturescompass:natures_compass_sapling": {
    "criteria": {
      "has_recipe": "2026-05-06 14:14:30 +1000"
    },
    "done": true
  },
  "notreepunching:flint_axe": {
    "criteria": {
      "has_the_recipe": "2026-05-06 14:14:30 +1000"
    },
    "done": true
  },
  "notreepunching:leather_from_leggings_with_knife": {
    "criteria": {
      "has_the_recipe": "2026-05-06 14:14:30 +1000"
    },
    "done": true
  },
  "notreepunching:diamond_knife": {
    "criteria": {
      "has_the_recipe": "2026-05-06 14:14:30 +1000"
    },
    "done": true
  },
  "notreepunching:netherite_knife": {
    "criteria": {
      "has_the_recipe": "2026-05-06 14:14:30 +1000"
    },
    "done": true
  },
  "notreepunching:netherite_saw": {
    "criteria": {
      "has_the_recipe": "2026-05-06 14:14:30 +1000"
    },
    "done": true
  },
  "cold_sweat:recipes/thermolith": {
    "criteria": {
      "has_recipe": "2026-05-06 14:14:30 +1000"
    },
    "done": true
  },
  "notreepunching:cobblestone_from_rocks": {
    "criteria": {
      "has_the_recipe": "2026-05-06 14:14:30 +1000"
    },
    "done": true
  },
  "lootr:root": {
    "criteria": {
      "always_true": "2026-05-06 14:14:30 +1000"
    },
    "done": true
  },
  "notreepunching:stonecutting/andesite_cobblestone_stairs": {
    "criteria": {
      "has_the_recipe": "2026-05-06 14:14:30 +1000"
    },
    "done": true
  },
  "notreepunching:iron_saw": {
    "criteria": {
      "has_the_recipe": "2026-05-06 14:14:30 +1000"
    },
    "done": true
  },
  "notreepunching:granite_cobblestone_from_rocks": {
    "criteria": {
      "has_the_recipe": "2026-05-06 14:14:30 +1000"
    },
    "done": true
  },
  "notreepunching:leather_from_boots_with_knife": {
    "criteria": {
      "has_the_recipe": "2026-05-06 14:14:30 +1000"
    },
    "done": true
  },
  "cold_sweat:recipes/waterskin": {
    "criteria": {
      "has_recipe": "2026-05-06 14:14:30 +1000"
    },
    "done": true
  },
  "naturescompass:repair_natures_compass": {
    "criteria": {
      "has_recipe": "2026-05-06 14:14:30 +1000"
    },
    "done": true
  },
  "notreepunching:plant_fiber_from_saplings_with_knife": {
    "criteria": {
      "has_the_recipe": "2026-05-06 14:14:30 +1000"
    },
    "done": true
  },
  "notreepunching:andesite_cobblestone_stairs": {
    "criteria": {
      "has_the_recipe": "2026-05-06 14:14:30 +1000"
    },
    "done": true
  },
  "notreepunching:sticks_from_logs_with_flint_axe": {
    "criteria": {
      "has_the_recipe": "2026-05-06 14:14:30 +1000"
    },
    "done": true
  },
  "notreepunching:sticks_from_planks_with_flint_axe": {
    "criteria": {
      "has_the_recipe": "2026-05-06 14:14:30 +1000"
    },
    "done": true
  },
  "cold_sweat:recipes/chameleon_armor": {
    "criteria": {
      "has_boots_recipe": "2026-05-06 14:14:30 +1000"
    },
    "done": true
  },
  "notreepunching:plant_fiber_from_leaves_with_knife": {
    "criteria": {
      "has_the_recipe": "2026-05-06 14:14:30 +1000"
    },
    "done": true
  },
  "notreepunching:flint_from_gravel": {
    "criteria": {
      "has_the_recipe": "2026-05-06 14:14:30 +1000"
    },
    "done": true
  },
  "notreepunching:andesite_cobblestone_slab": {
    "criteria": {
      "has_the_recipe": "2026-05-06 14:14:30 +1000"
    },
    "done": true
  },
  "cold_sweat:recipes/thermometer": {
    "criteria": {
      "has_recipe": "2026-05-06 14:14:30 +1000"
    },
    "done": true
  },
  "notreepunching:string_from_wool_with_knife": {
    "criteria": {
      "has_the_recipe": "2026-05-06 14:14:30 +1000"
    },
    "done": true
  },
  "notreepunching:plant_fiber_from_vines_with_knife": {
    "criteria": {
      "has_the_recipe": "2026-05-06 14:14:30 +1000"
    },
    "done": true
  },
  "notreepunching:plant_fiber_from_cactus_with_knife": {
    "criteria": {
      "has_the_recipe": "2026-05-06 14:14:30 +1000"
    },
    "done": true
  },
  "notreepunching:iron_knife": {
    "criteria": {
      "has_the_recipe": "2026-05-06 14:14:30 +1000"
    },
    "done": true
  },
  "minecraft:adventure/adventuring_time": {
    "criteria": {
      "minecraft:snowy_slopes": "2026-05-06 14:14:31 +1000"
    },
    "done": false
  },
  "DataVersion": 3465
}